oshinko_temaki/__init__.py
oshinko_temaki/cli.py
oshinko_temaki/configs.py
oshinko_temaki/templates.py
oshinko_temaki-0.4.1.dist-info/AUTHORS
oshinko_temaki-0.4.1.dist-info/LICENSE
oshinko_temaki-0.4.1.dist-info/METADATA
oshinko_temaki-0.4.1.dist-info/WHEEL
oshinko_temaki-0.4.1.dist-info/entry_points.txt
oshinko_temaki-0.4.1.dist-info/pbr.json
oshinko_temaki-0.4.1.dist-info/top_level.txt
oshinko_temaki-0.4.1.dist-info/RECORD
