Metadata-Version: 2.1
Name: oshinko-temaki
Version: 0.4.1
Summary: a tool for hand rolling Apache Spark clusters
Home-page: https://github.com/elmiko/oshinko-temaki
License: Apache-2
Platform: UNKNOWN
Classifier: Development Status :: 4 - Beta
Classifier: Environment :: Console
Classifier: Intended Audience :: Developers
Classifier: License :: OSI Approved :: Apache Software License
Classifier: Operating System :: OS Independent
Classifier: Programming Language :: Python :: 3
Requires-Dist: PyYAML (>=4.2b1)
